dismusic/__init__.py
dismusic/_classes.py
dismusic/_emojis.py
dismusic/_version.py
dismusic/checks.py
dismusic/errors.py
dismusic/events.py
dismusic/music.py
dismusic/paginator.py
dismusic/player.py
dismusic-1.2.1.dist-info/LICENSE
dismusic-1.2.1.dist-info/METADATA
dismusic-1.2.1.dist-info/WHEEL
dismusic-1.2.1.dist-info/top_level.txt
dismusic-1.2.1.dist-info/RECORD
