Metadata-Version: 2.1
Name: dismusic
Version: 1.2.1
Summary: Music cog for discord bots. Supports YouTube, YoutubeMusic, SoundCloud and Spotify.
Home-page: https://github.com/shahriyardx/dismusic/
Author: Md Shahriyar Alam
Author-email: contact@shahriyar.dev
License: MIT
Project-URL: Bug Reports, https://github.com/shahriyardx/dismusic/issues
Project-URL: Source, https://github.com/shahriyardx/dismusic/
Keywords: discord discord-music music-bot discord-music-bot lavalink wavelink
Platform: UNKNOWN
Classifier: Development Status :: 5 - Production/Stable
Classifier: Intended Audience :: Developers
Classifier: Framework :: aiohttp
Classifier: Operating System :: MacOS
Classifier: Operating System :: POSIX :: Linux
Classifier: Operating System :: Microsoft :: Windows
Classifier: License :: OSI Approved :: MIT License
Classifier: Programming Language :: Python :: 3.7
Classifier: Programming Language :: Python :: 3.8
Classifier: Programming Language :: Python :: 3.9
Classifier: Programming Language :: Python :: 3.10
Requires-Python: >=3.7, <4
License-File: LICENSE
Requires-Dist: aiohttp (>=3.8.1)
Requires-Dist: async-timeout (>=4.0.2)
Requires-Dist: wavelink (>=1.2.4)
